<annotation verified="no">
  <folder>split_1_all_images</folder>
  <filename>ship0201610150201902</filename>
  <path>ship0201610150201902.xml</path> 
  <source>
    <database>Unknown</database>
  </source>
  <size>
    <width>256</width>
    <height>256</height>
    <depth>3</depth>
  </size>
  <segmented>0</segmented>
  <object>
    <name>ship</name>
    <pose>Unspecified</pose>
    <truncated>0</truncated>
    <Difficult>0</Difficult>
    <bndbox>
      <xmin>62</xmin>
      <ymin>143</ymin>
      <xmax>84</xmax>
      <ymax>182</ymax>
    </bndbox>
  </object>
  <object>
    <name>ship</name>
    <pose>Unspecified</pose>
    <truncated>0</truncated>
    <Difficult>0</Difficult>
    <bndbox>
      <xmin>41</xmin>
      <ymin>137</ymin>
      <xmax>61</xmax>
      <ymax>179</ymax>
    </bndbox>
  </object>
</annotation>
