<annotation verified="no">
  <folder>2016092802</folder>
  <filename>ship02016092802045031</filename>
  <path>ship02016092802045031.xml</path> 
  <source>
    <database>Unknown</database>
  </source>
  <size>
    <width>256</width>
    <height>256</height>
    <depth>3</depth>
  </size>
  <segmented>0</segmented>
  <object>
    <name>ship</name>
    <pose>Unspecified</pose>
    <truncated>0</truncated>
    <Difficult>0</Difficult>
    <bndbox>
      <xmin>211</xmin>
      <ymin>79</ymin>
      <xmax>254</xmax>
      <ymax>111</ymax>
    </bndbox>
  </object>
  <object>
    <name>ship</name>
    <pose>Unspecified</pose>
    <truncated>0</truncated>
    <Difficult>0</Difficult>
    <bndbox>
      <xmin>169</xmin>
      <ymin>123</ymin>
      <xmax>179</xmax>
      <ymax>175</ymax>
    </bndbox>
  </object>
  <object>
    <name>ship</name>
    <pose>Unspecified</pose>
    <truncated>0</truncated>
    <Difficult>0</Difficult>
    <bndbox>
      <xmin>160</xmin>
      <ymin>27</ymin>
      <xmax>203</xmax>
      <ymax>73</ymax>
    </bndbox>
  </object>
</annotation>
