<annotation verified="no">
  <folder>20160908</folder>
  <filename>ship020160908023034</filename>
  <path>ship020160908023034.xml</path> 
  <source>
    <database>Unknown</database>
  </source>
  <size>
    <width>256</width>
    <height>256</height>
    <depth>3</depth>
  </size>
  <segmented>0</segmented>
  <object>
    <name>ship</name>
    <pose>Unspecified</pose>
    <truncated>0</truncated>
    <Difficult>0</Difficult>
    <bndbox>
      <xmin>157</xmin>
      <ymin>150</ymin>
      <xmax>170</xmax>
      <ymax>219</ymax>
    </bndbox>
  </object>
</annotation>
