<annotation verified="no">
  <folder>2018011901</folder>
  <filename>ship02018011901034011</filename>
  <path>ship02018011901034011.xml</path> 
  <source>
    <database>Unknown</database>
  </source>
  <size>
    <width>256</width>
    <height>256</height>
    <depth>3</depth>
  </size>
  <segmented>0</segmented>
  <object>
    <name>ship</name>
    <pose>Unspecified</pose>
    <truncated>0</truncated>
    <Difficult>0</Difficult>
    <bndbox>
      <xmin>74</xmin>
      <ymin>218</ymin>
      <xmax>117</xmax>
      <ymax>233</ymax>
    </bndbox>
  </object>
</annotation>
