<annotation verified="no">
  <folder>split_1_all_images</folder>
  <filename>ship0201701310202805</filename>
  <path>ship0201701310202805.xml</path> 
  <source>
    <database>Unknown</database>
  </source>
  <size>
    <width>256</width>
    <height>256</height>
    <depth>3</depth>
  </size>
  <segmented>0</segmented>
  <object>
    <name>ship</name>
    <pose>Unspecified</pose>
    <truncated>0</truncated>
    <Difficult>0</Difficult>
    <bndbox>
      <xmin>146</xmin>
      <ymin>51</ymin>
      <xmax>167</xmax>
      <ymax>63</ymax>
    </bndbox>
  </object>
  <object>
    <name>ship</name>
    <pose>Unspecified</pose>
    <truncated>0</truncated>
    <Difficult>0</Difficult>
    <bndbox>
      <xmin>164</xmin>
      <ymin>65</ymin>
      <xmax>181</xmax>
      <ymax>79</ymax>
    </bndbox>
  </object>
  <object>
    <name>ship</name>
    <pose>Unspecified</pose>
    <truncated>0</truncated>
    <Difficult>0</Difficult>
    <bndbox>
      <xmin>224</xmin>
      <ymin>175</ymin>
      <xmax>255</xmax>
      <ymax>200</ymax>
    </bndbox>
  </object>
</annotation>
