<annotation verified="no">
  <folder>20170823</folder>
  <filename>ship020170823048036</filename>
  <path>ship020170823048036.xml</path> 
  <source>
    <database>Unknown</database>
  </source>
  <size>
    <width>256</width>
    <height>256</height>
    <depth>3</depth>
  </size>
  <segmented>0</segmented>
  <object>
    <name>ship</name>
    <pose>Unspecified</pose>
    <truncated>0</truncated>
    <Difficult>0</Difficult>
    <bndbox>
      <xmin>130</xmin>
      <ymin>130</ymin>
      <xmax>184</xmax>
      <ymax>179</ymax>
    </bndbox>
  </object>
</annotation>
